genjwtkey/__init__.py
genjwtkey/__main__.py
genjwtkey/generate.py
genjwtkey-1.0.dist-info/LICENSE
genjwtkey-1.0.dist-info/METADATA
genjwtkey-1.0.dist-info/WHEEL
genjwtkey-1.0.dist-info/top_level.txt
genjwtkey-1.0.dist-info/RECORD
