Metadata-Version: 2.1
Name: genjwtkey
Version: 1.0
Summary: "This package is a generator of assertion key pair for LINE Bot."
Home-page: UNKNOWN
Author: Wataru Nishimura
Author-email: wataru.nishimura@irenkakotan.co.jp
License: UNKNOWN
Platform: UNKNOWN
Requires-Python: >=3.4
License-File: LICENSE
Requires-Dist: jwcrypto
Requires-Dist: pathlib
